pyct/.version
pyct/__init__.py
pyct/__main__.py
pyct/build.py
pyct/cmd.py
pyct/report.py
pyct/tests/__init__.py
pyct/tests/test_cmd.py
pyct/tests/test_report.py
pyct-0.5.0.dist-info/LICENSE.txt
pyct-0.5.0.dist-info/METADATA
pyct-0.5.0.dist-info/WHEEL
pyct-0.5.0.dist-info/entry_points.txt
pyct-0.5.0.dist-info/top_level.txt
pyct-0.5.0.dist-info/RECORD
