Metadata-Version: 2.1
Name: pyct
Version: 0.5.0
Summary: Python package common tasks for users (e.g. copy examples, fetch data, ...)
Home-page: https://github.com/pyviz-dev/pyct
Author: HoloViz
Author-email: developers@holoviz.org
Maintainer: HoloViz
Maintainer-email: developers@holoviz.org
License: BSD 3-Clause License
Project-URL: Bug Tracker, https://github.com/pyviz-dev/pyct/issues
Project-URL: Source Code, https://github.com/pyviz-dev/pyct
Classifier: License :: OSI Approved :: BSD License
Classifier: Operating System :: OS Independent
Classifier: Programming Language :: Python
Classifier: Programming Language :: Python :: 3.7
Classifier: Programming Language :: Python :: 3.8
Classifier: Programming Language :: Python :: 3.9
Classifier: Programming Language :: Python :: 3.10
Classifier: Programming Language :: Python :: 3.11
Classifier: Development Status :: 4 - Beta
Requires-Python: >=3.7
Provides-Extra: cmd
Provides-Extra: tests
Provides-Extra: doc
Provides-Extra: build
License-File: LICENSE.txt
